PyRemoveDuplicates/__init__.py
PyRemoveDuplicates-0.2.dist-info/LICENSE.txt
PyRemoveDuplicates-0.2.dist-info/METADATA
PyRemoveDuplicates-0.2.dist-info/WHEEL
PyRemoveDuplicates-0.2.dist-info/top_level.txt
PyRemoveDuplicates-0.2.dist-info/RECORD
