Metadata-Version: 2.1
Name: PyRemoveDuplicates
Version: 0.2
Summary: Remove all duplicates value from an array
Home-page: https://pypi.org/project/PyRemoveDuplicates/
Author: Md. Ismiel Hossen Abir
License: MIT
License-File: LICENSE.txt
